tt42/__init__.py
tt42-0.0.dist-info/METADATA
tt42-0.0.dist-info/WHEEL
tt42-0.0.dist-info/top_level.txt
tt42-0.0.dist-info/RECORD
