Metadata-Version: 2.1
Name: tt42
Version: 0.0
Summary: asdasdasd
Home-page: UNKNOWN
Author: qdzzzxc
Author-email: 
License: UNKNOWN
Platform: UNKNOWN
Classifier: Programming Language :: Python :: 3
Classifier: License :: OSI Approved :: MIT License
Classifier: Operating System :: OS Independent
Requires-Python: >=3.6
